rhymepy/__init__.py
rhymepy/apis.py
rhymepy/default_rhymepy.ini
rhymepy/main.py
rhymepy/parse.py
rhymepy-0.1.0.dist-info/LICENSE
rhymepy-0.1.0.dist-info/METADATA
rhymepy-0.1.0.dist-info/WHEEL
rhymepy-0.1.0.dist-info/entry_points.txt
rhymepy-0.1.0.dist-info/top_level.txt
rhymepy-0.1.0.dist-info/RECORD
