Metadata-Version: 2.1
Name: rhymepy
Version: 0.1.0
Summary: A simple CLI program that highlights rhymes in a given text
Home-page: https://github.com/dimeritium-foil/rhymepy
Author: Farris Essam
License: UNKNOWN
Platform: UNKNOWN
Requires-Dist: colored
Requires-Dist: requests
Provides-Extra: native_rhymes_matching_via_the_pronouncing_module.
Requires-Dist: pronouncing ; extra == 'native_rhymes_matching_via_the_pronouncing_module.'
